infix.py
infix-1.2.dist-info/DESCRIPTION.rst
infix-1.2.dist-info/METADATA
infix-1.2.dist-info/RECORD
infix-1.2.dist-info/WHEEL
infix-1.2.dist-info/metadata.json
infix-1.2.dist-info/top_level.txt
